permanence/__init__.py
permanence/artifact.py
permanence/chunks.py
permanence/namespace.py
permanence/object.py
permanence/record_type.py
permanence/scope_type.py
permanence/tag_type.py
permanence/diff/__init__.py
permanence/diff/bounds.py
permanence/diff/viewer.py
permanence-0.1.1.dist-info/METADATA
permanence-0.1.1.dist-info/WHEEL
permanence-0.1.1.dist-info/RECORD
